zweig.py
zweig-0.1.0.dist-info/DESCRIPTION.rst
zweig-0.1.0.dist-info/METADATA
zweig-0.1.0.dist-info/pydist.json
zweig-0.1.0.dist-info/RECORD
zweig-0.1.0.dist-info/top_level.txt
zweig-0.1.0.dist-info/WHEEL
