Metadata-Version: 2.0
Name: zweig
Version: 0.1.0
Summary: Utilities for dealing with the ast module
Home-page: https://github.com/DasIch/zweig
Author: Daniel Neuhäuser
Author-email: ich@daniel.neuhaeuser.de
License: UNKNOWN
Platform: UNKNOWN
